LICENSE
README.md
setup.py
easycron/__init__.py
easycron/core.py
pyeasycron.egg-info/PKG-INFO
pyeasycron.egg-info/SOURCES.txt
pyeasycron.egg-info/dependency_links.txt
pyeasycron.egg-info/requires.txt
pyeasycron.egg-info/top_level.txt
test/test_common.py
test/test_concurrency.py
test/test_cron.py
test/test_interval.py
test/test_mix.py