Metadata-Version: 2.1
Name: pyeasycron
Version: 0.2.0
Summary: An easy way to make function run as cron
Home-page: https://github.com/wyn-ying/pyeasycron
Author: wyn-ying
Author-email: yingwen.wyn@gmail.com
Keywords: easycron,cron,cronjob,schedule,automation
Classifier: Programming Language :: Python
Classifier: License :: OSI Approved :: MIT License
Classifier: Operating System :: OS Independent
Classifier: Programming Language :: Python :: 3.7
Classifier: Programming Language :: Python :: 3.8
Classifier: Programming Language :: Python :: 3.9
Classifier: Programming Language :: Python :: 3.10
Classifier: Programming Language :: Python :: 3.11
Classifier: Programming Language :: Python :: 3.12
License-File: LICENSE
Requires-Dist: croniter
